palschema/__init__.py
palschema/interface_schema.py
palschema/pearl_schema.py
palschema-0.1.0.dist-info/entry_points.txt
palschema-0.1.0.dist-info/licenses/LICENSE.txt
palschema-0.1.0.dist-info/WHEEL
palschema-0.1.0.dist-info/METADATA
palschema-0.1.0.dist-info/RECORD
