Metadata-Version: 2.4
Name: palschema
Version: 0.1.0
Summary: A schema lib
Author-email: Tiny Twist <tiny.mahua@gmail.com>
Maintainer-email: Tiny Twist <tiny.mahua@gmail.com>
Requires-Python: >= 3.6
License-File: LICENSE.txt
